transip/__init__.py
transip/client.py
transip/transip_cli.py
transip/service/__init__.py
transip/service/domain.py
transip/service/haip.py
transip/service/objects.py
transip/service/vps.py
transip/service/webhosting.py
transip-2.1.2.dist-info/LICENSE
transip-2.1.2.dist-info/METADATA
transip-2.1.2.dist-info/WHEEL
transip-2.1.2.dist-info/entry_points.txt
transip-2.1.2.dist-info/top_level.txt
transip-2.1.2.dist-info/RECORD
