Metadata-Version: 2.1
Name: transip
Version: 2.1.2
Summary: TransIP API Connector
Home-page: https://github.com/benkonrath/transip-api
Author: Go About B.V.
Author-email: tech@goabout.com
Maintainer: Ben Konrath
Maintainer-email: ben@bagu.org
License: MIT
Platform: all
Classifier: Development Status :: 4 - Beta
Classifier: Intended Audience :: Developers
Classifier: License :: OSI Approved :: MIT License
Classifier: Operating System :: OS Independent
Classifier: Programming Language :: Python
Classifier: Programming Language :: Python :: 2.7
Classifier: Programming Language :: Python :: 3.4
Classifier: Programming Language :: Python :: 3.5
Classifier: Programming Language :: Python :: 3.6
Classifier: Programming Language :: Python :: 3.7
Classifier: Programming Language :: Python :: 3.8
Classifier: Topic :: Utilities
Requires-Dist: requests
Requires-Dist: cryptography
Requires-Dist: suds-jurko
